{"_type":"export","__export_format":4,"__export_date":"2023-01-27T03:06:07.646Z","__export_source":"insomnia.desktop.app:v2022.7.5","resources":[{"_id":"req_6bdd12a1965842fca25f8467b9508295","parentId":"fld_93def7d2b74a4c27bcb9e72d9000e096","modified":1674787899884,"created":1674786659172,"url":"{{ _.base_url }}/upload","name":"New Request","description":"","method":"POST","body":{"mimeType":"multipart/form-data","params":[{"id":"pair_f0d931704cb14fe7b5b3850a935384e1","name":"fileUpload","value":"","description":"","type":"file","fileName":"C:\\Users\\moise\\OneDrive\\Imagens\\perfil.jpeg"}]},"parameters":[],"headers":[{"name":"Content-Type","value":"multipart/form-data"}],"authentication":{},"metaSortKey":-1674786659172,"isPrivate":false,"settingStoreCookies":true,"settingSendCookies":true,"settingDisableRenderRequestBody":false,"settingEncodeUrl":true,"settingRebuildPath":true,"settingFollowRedirects":"global","_type":"request"},{"_id":"fld_93def7d2b74a4c27bcb9e72d9000e096","parentId":"wrk_43783c1ee4264ebfa4cb35818cc2ff7a","modified":1674786654398,"created":1674786654398,"name":"Upload","description":"","environment":{},"environmentPropertyOrder":null,"metaSortKey":-1674786654398,"_type":"request_group"},{"_id":"wrk_43783c1ee4264ebfa4cb35818cc2ff7a","parentId":null,"modified":1674662892436,"created":1674662892436,"name":"Api-Lavras","description":"","scope":"collection","_type":"workspace"},{"_id":"req_c6b5f013493a4a2ea74b471f72a29423","parentId":"fld_0b5a67b891a648fe9299e6bc53b8cd95","modified":1674785805984,"created":1674785765211,"url":"{{ _.base_url }}/criancas/2","name":"delete","description":"","method":"DELETE","body":{},"parameters":[],"headers":[],"authentication":{},"metaSortKey":-1674785765211,"isPrivate":false,"settingStoreCookies":true,"settingSendCookies":true,"settingDisableRenderRequestBody":false,"settingEncodeUrl":true,"settingRebuildPath":true,"settingFollowRedirects":"global","_type":"request"},{"_id":"fld_0b5a67b891a648fe9299e6bc53b8cd95","parentId":"wrk_43783c1ee4264ebfa4cb35818cc2ff7a","modified":1674761460684,"created":1674761460684,"name":"Childrens","description":"","environment":{},"environmentPropertyOrder":null,"metaSortKey":-1674761460684,"_type":"request_group"},{"_id":"req_183ed685c9fa403abbea555dd148bf6a","parentId":"fld_0b5a67b891a648fe9299e6bc53b8cd95","modified":1674784839973,"created":1674784763845,"url":"{{ _.base_url }}/criancas/1","name":"update","description":"","method":"PUT","body":{"mimeType":"application/json","text":"{\n\t\"nameChildren\": \"Hadassah Samira editada\"\n}"},"parameters":[],"headers":[{"name":"Content-Type","value":"application/json"}],"authentication":{},"metaSortKey":-1674784763845,"isPrivate":false,"settingStoreCookies":true,"settingSendCookies":true,"settingDisableRenderRequestBody":false,"settingEncodeUrl":true,"settingRebuildPath":true,"settingFollowRedirects":"global","_type":"request"},{"_id":"req_b59d26c719d4470ab5a9c1dd9de38dab","parentId":"fld_0b5a67b891a648fe9299e6bc53b8cd95","modified":1674785982870,"created":1674761489613,"url":"{{ _.base_url }}/criancas","name":"index","description":"","method":"GET","body":{},"parameters":[],"headers":[{"id":"pair_a93d9abe06e3493f834f1f178a9ea31c","name":"authorization","value":"Bearer eyJhbGciOiJIUzI1NiIsInR5cCI6IkpXVCJ9.eyJpZCI6MTYsImxvZ2luIjoianNvbiIsImlhdCI6MTY3NDc0Nzc4NywiZXhwIjoxNjc0ODM0MTg3fQ.ZjfakEYREXTZevHUq-aRrNyM-dGJdziEIHyaaiXf8lI","description":""}],"authentication":{},"metaSortKey":-1674761489613,"isPrivate":false,"settingStoreCookies":true,"settingSendCookies":true,"settingDisableRenderRequestBody":false,"settingEncodeUrl":true,"settingRebuildPath":true,"settingFollowRedirects":"global","_type":"request"},{"_id":"req_04aabacd284b41739a3ee1e1730b569a","parentId":"fld_0b5a67b891a648fe9299e6bc53b8cd95","modified":1674784335264,"created":1674774688470,"url":"{{ _.base_url }}/criancas","name":"store","description":"","method":"POST","body":{"mimeType":"application/json","text":"{\n\t\"nameChildren\": \"Yahnn Henrique\",\n\t\"age\": \"02\",\n\t\"nameGuardianOne\": \"Karem Samira\",\n\t\"nameGuardianTwo\": \"Moises Henrique\",\n\t\"phone\": \" 11 989408922\",\n\t\"passwordEntry\": \"1234\",\n\t\"passwordOut\": \"1234\"\n}"},"parameters":[],"headers":[{"name":"Content-Type","value":"application/json"}],"authentication":{},"metaSortKey":-1674761489563,"isPrivate":false,"settingStoreCookies":true,"settingSendCookies":true,"settingDisableRenderRequestBody":false,"settingEncodeUrl":true,"settingRebuildPath":true,"settingFollowRedirects":"global","_type":"request"},{"_id":"req_c05f00bdabe247bda18d6531024a07c9","parentId":"wrk_43783c1ee4264ebfa4cb35818cc2ff7a","modified":1674784494758,"created":1674784397895,"url":"{{ _.base_url }}/criancas/1","name":"show","description":"","method":"GET","body":{},"parameters":[],"headers":[],"authentication":{},"metaSortKey":-1674723251394,"isPrivate":false,"settingStoreCookies":true,"settingSendCookies":true,"settingDisableRenderRequestBody":false,"settingEncodeUrl":true,"settingRebuildPath":true,"settingFollowRedirects":"global","_type":"request"},{"_id":"req_eb013a46bc8d45f3ad7ccec150823fba","parentId":"fld_ba55bbd8901047ddb636757fcae7411a","modified":1674747828499,"created":1674747689814,"url":"{{ _.base_url }}/usuarios","name":"index","description":"","method":"GET","body":{},"parameters":[],"headers":[{"id":"pair_4dd39b3b11f54c7fa62029b7820b8de1","name":"authorization","value":"Bearer eyJhbGciOiJIUzI1NiIsInR5cCI6IkpXVCJ9.eyJpZCI6MTYsImxvZ2luIjoianNvbiIsImlhdCI6MTY3NDc0Nzc4NywiZXhwIjoxNjc0ODM0MTg3fQ.ZjfakEYREXTZevHUq-aRrNyM-dGJdziEIHyaaiXf8lI","description":""}],"authentication":{},"metaSortKey":-1674747689814,"isPrivate":false,"settingStoreCookies":true,"settingSendCookies":true,"settingDisableRenderRequestBody":false,"settingEncodeUrl":true,"settingRebuildPath":true,"settingFollowRedirects":"global","_type":"request"},{"_id":"fld_ba55bbd8901047ddb636757fcae7411a","parentId":"wrk_43783c1ee4264ebfa4cb35818cc2ff7a","modified":1674685042104,"created":1674685042104,"name":"Users","description":"","environment":{},"environmentPropertyOrder":null,"metaSortKey":-1674685042104,"_type":"request_group"},{"_id":"req_3510024b178d4f1dbddcbb6d641c4c80","parentId":"fld_ebe7c96b09fa4f74ac084ebc99448c97","modified":1674747785035,"created":1674747734918,"url":"{{ _.base_url }}/tokens","name":"New Request","description":"","method":"POST","body":{"mimeType":"application/json","text":"{\n\t\"login\": \"json\" ,\n\t\"password\": \"123456\"\n}"},"parameters":[],"headers":[{"name":"Content-Type","value":"application/json"}],"authentication":{},"metaSortKey":-1674747734918,"isPrivate":false,"settingStoreCookies":true,"settingSendCookies":true,"settingDisableRenderRequestBody":false,"settingEncodeUrl":true,"settingRebuildPath":true,"settingFollowRedirects":"global","_type":"request"},{"_id":"fld_ebe7c96b09fa4f74ac084ebc99448c97","parentId":"wrk_43783c1ee4264ebfa4cb35818cc2ff7a","modified":1674700396014,"created":1674697432791,"name":"Tokens","description":"","environment":{},"environmentPropertyOrder":null,"metaSortKey":-1674675402661.5,"_type":"request_group"},{"_id":"env_8bd5cd19c3425a6064df73656deca97405177dc6","parentId":"wrk_43783c1ee4264ebfa4cb35818cc2ff7a","modified":1674693263431,"created":1674662892449,"name":"Base Environment","data":{"base_url":"http://localhost:3001"},"dataPropertyOrder":{"&":["base_url"]},"color":null,"isPrivate":false,"metaSortKey":1674662892449,"_type":"environment"},{"_id":"jar_8bd5cd19c3425a6064df73656deca97405177dc6","parentId":"wrk_43783c1ee4264ebfa4cb35818cc2ff7a","modified":1674662892454,"created":1674662892454,"name":"Default Jar","cookies":[],"_type":"cookie_jar"},{"_id":"spc_9cf3e6df85d344349af2960733ac4868","parentId":"wrk_43783c1ee4264ebfa4cb35818cc2ff7a","modified":1674662892437,"created":1674662892437,"fileName":"Api-Lavras","contents":"","contentType":"yaml","_type":"api_spec"}]}